od_metrics/__init__.py
od_metrics/constants.py
od_metrics/od_metrics.py
od_metrics/utils.py
od_metrics/validators.py
od_metrics-2.2.0.dist-info/licenses/LICENSE
od_metrics-2.2.0.dist-info/METADATA
od_metrics-2.2.0.dist-info/WHEEL
od_metrics-2.2.0.dist-info/top_level.txt
od_metrics-2.2.0.dist-info/RECORD
