Metadata-Version: 2.4
Name: od-metrics
Version: 2.2.0
Summary: Object Detection metrics.
Home-page: https://github.com/EMalagoli92/OD-metrics
Author: EMalagoli92
Author-email: emala.892@gmail.com
Classifier: Programming Language :: Python :: 3
Classifier: License :: OSI Approved :: Apache Software License
Classifier: Operating System :: OS Independent
Requires-Python: >=3.9
License-File: LICENSE
Requires-Dist: numpy==1.24.3
Requires-Dist: parameterized==0.9.0
Requires-Dist: pydantic<3.0,>=2.5.2
Dynamic: license-file
